nlu/__init__.py
nlu/discovery.py
nlu/finance.py
nlu/info.py
nlu/spellbook.py
nlu/test_file.py
nlu/components/__init__.py
nlu/components/assertions/__init__.py
nlu/components/assertions/assertion_dl/__init__.py
nlu/components/assertions/assertion_dl/assertion_dl.py
nlu/components/assertions/assertion_log_reg/__init__.py
nlu/components/assertions/assertion_log_reg/assertion_log_reg.py
nlu/components/chunkers/__init__.py
nlu/components/chunkers/chunk_mapper/__init__.py
nlu/components/chunkers/chunk_mapper/chunk_mapper.py
nlu/components/chunkers/contextual_parser/__init__.py
nlu/components/chunkers/contextual_parser/contextual_parser.py
nlu/components/chunkers/default_chunker/__init__.py
nlu/components/chunkers/default_chunker/default_chunker.py
nlu/components/chunkers/ngram/__init__.py
nlu/components/chunkers/ngram/ngram.py
nlu/components/classifiers/__init__.py
nlu/components/classifiers/asr/__init__.py
nlu/components/classifiers/asr/wav2Vec.py
nlu/components/classifiers/asr_hubert/__init__.py
nlu/components/classifiers/asr_hubert/hubert.py
nlu/components/classifiers/asr_whisper/__init__.py
nlu/components/classifiers/asr_whisper/whisper.py
nlu/components/classifiers/bert_zero_shot_classification/__init__.py
nlu/components/classifiers/bert_zero_shot_classification/bert_zero_shot.py
nlu/components/classifiers/classifier_dl/__init__.py
nlu/components/classifiers/classifier_dl/classifier_dl.py
nlu/components/classifiers/distil_bert_zero_shot_classification/__init__.py
nlu/components/classifiers/distil_bert_zero_shot_classification/distil_bert_zero_shot.py
nlu/components/classifiers/generic_classifier/__init__.py
nlu/components/classifiers/generic_classifier/generic_classifier.py
nlu/components/classifiers/image_classification_swin/__init__.py
nlu/components/classifiers/image_classification_swin/swin.py
nlu/components/classifiers/image_classification_vit/__init__.py
nlu/components/classifiers/image_classification_vit/convnext_image_classification.py
nlu_by_samed-5.1.4.dist-info/LICENSE
nlu_by_samed-5.1.4.dist-info/METADATA
nlu_by_samed-5.1.4.dist-info/WHEEL
nlu_by_samed-5.1.4.dist-info/top_level.txt
nlu_by_samed-5.1.4.dist-info/RECORD
